escape_unk/__init__.py
escape_unk/escape_unk.py
escape_unk/unescape_unk.py
escape_unk/utils.py
escape_unk-1.5.dist-info/LICENSE
escape_unk-1.5.dist-info/METADATA
escape_unk-1.5.dist-info/WHEEL
escape_unk-1.5.dist-info/entry_points.txt
escape_unk-1.5.dist-info/top_level.txt
escape_unk-1.5.dist-info/RECORD
