Metadata-Version: 2.2
Name: escape-unk
Version: 1.5
Summary: Escape unknown symbols in SentecePiece vocabularies
Author-email: Jaume Zaragoza <jzaragoza@prompsit.com>
Project-URL: HomePage, https://github.com/ZJaume/escape-unk
Requires-Python: >=3.7
License-File: LICENSE
Requires-Dist: regex
Requires-Dist: sentencepiece<=0.2
Requires-Dist: protobuf<6
